ytkd_api.py
ytkd_api-0.0.3.dist-info/License
ytkd_api-0.0.3.dist-info/METADATA
ytkd_api-0.0.3.dist-info/WHEEL
ytkd_api-0.0.3.dist-info/top_level.txt
ytkd_api-0.0.3.dist-info/RECORD
