Metadata-Version: 2.1
Name: ytkd-api
Version: 0.0.3
Summary: A Python wrapper for YouTube Key word detection API. 
Home-page: https://github.com/alinisarhaider/ytkd_api
Author: Ali Haider
Author-email: alinisarhaider@gmail.com
License: UNKNOWN
Platform: UNKNOWN
Classifier: Programming Language :: Python :: 3
Classifier: License :: OSI Approved :: MIT License
Classifier: Operating System :: OS Independent
Requires-Python: >=3.6
Requires-Dist: requests
